{
  "139320": {
    "name": "TIGER 금은선물(H)",
    "price": 20800,
    "diff": 70,
    "pct": 0.34
  },
  "229200": {
    "name": "KODEX 코스닥150",
    "price": 19525,
    "diff": 110,
    "pct": 0.57
  },
  "498400": {
    "name": "KODEX 200타겟위클리커버드콜",
    "price": 19145,
    "diff": 285,
    "pct": 1.51
  },
  "472150": {
    "name": "TIGER 배당커버드콜액티브",
    "price": 19400,
    "diff": 350,
    "pct": 1.84
  },
  "441640": {
    "name": "KODEX 미국배당커버드콜액티브",
    "price": 12845,
    "diff": 0,
    "pct": 0.0
  },
  "483320": {
    "name": "ACE 엔비디아밸류체인액티브",
    "price": 21000,
    "diff": 195,
    "pct": 0.94
  },
  "426030": {
    "name": "TIME 미국나스닥100액티브",
    "price": 43965,
    "diff": 600,
    "pct": 1.38
  },
  "491620": {
    "name": "RISE 미국테크100데일리고정커버드콜",
    "price": 10960,
    "diff": 225,
    "pct": 2.1
  },
  "478150": {
    "name": "TIME 글로벌우주테크&방산액티브",
    "price": 22590,
    "diff": 40,
    "pct": 0.18
  },
  "0131V0": {
    "name": "1Q 미국우주항공테크",
    "price": 12905,
    "diff": 260,
    "pct": 2.06
  },
  "0040X0": {
    "name": "SOL 팔란티어미국채커버드콜혼합",
    "price": 10160,
    "diff": 110,
    "pct": 1.09
  },
  "0023A0": {
    "name": "SOL 미국양자컴퓨팅TOP10",
    "price": 28365,
    "diff": 2850,
    "pct": 11.17
  },
  "0117V0": {
    "name": "TIGER 코리아AI전력기기TOP3플러스",
    "price": 20290,
    "diff": 270,
    "pct": 1.35
  },
  "456600": {
    "name": "TIME 글로벌AI인공지능액티브",
    "price": 49045,
    "diff": 820,
    "pct": 1.7
  },
  "490590": {
    "name": "RISE 미국AI밸류체인데일리고정커버드콜",
    "price": 14210,
    "diff": 275,
    "pct": 1.97
  },
  "493810": {
    "name": "TIGER 미국AI빅테크10타겟데일리커버드콜",
    "price": 12020,
    "diff": 280,
    "pct": 2.39
  },
  "483330": {
    "name": "ACE 마이크로소프트밸류체인액티브",
    "price": 13270,
    "diff": 450,
    "pct": 3.51
  },
  "396500": {
    "name": "TIGER 반도체TOP10",
    "price": 35950,
    "diff": 460,
    "pct": 1.3
  },
  "0093A0": {
    "name": "RISE AI반도체TOP10",
    "price": 33545,
    "diff": 345,
    "pct": 1.04
  },
  "475300": {
    "name": "SOL 반도체전공정",
    "price": 19205,
    "diff": 340,
    "pct": 1.8
  },
  "395270": {
    "name": "HANARO Fn K-반도체",
    "price": 40185,
    "diff": 715,
    "pct": 1.81
  },
  "449450": {
    "name": "PLUS K방산",
    "price": 79150,
    "diff": 655,
    "pct": 0.83
  },
  "490480": {
    "name": "SOL K방산",
    "price": 39835,
    "diff": 455,
    "pct": 1.16
  },
  "0080G0": {
    "name": "KODEX 방산TOP10",
    "price": 15090,
    "diff": 120,
    "pct": 0.8
  },
  "494670": {
    "name": "TIGER 조선TOP10",
    "price": 28095,
    "diff": 695,
    "pct": 2.54
  },
  "480030": {
    "name": "ACE 미국500데일리타겟커버드콜(합성)",
    "price": 10720,
    "diff": 95,
    "pct": 0.89
  },
  "0115D0": {
    "name": "KODEX 조선TOP10",
    "price": 9715,
    "diff": 215,
    "pct": 2.26
  },
  "305540": {
    "name": "TIGER 2차전지테마",
    "price": 22590,
    "diff": 450,
    "pct": 2.03
  },
  "305720": {
    "name": "KODEX 2차전지산업",
    "price": 18295,
    "diff": 350,
    "pct": 1.95
  },
  "232080": {
    "name": "TIGER 코스닥150",
    "price": 19930,
    "diff": 125,
    "pct": 0.63
  },
  "270810": {
    "name": "RISE 코스닥150",
    "price": 19390,
    "diff": 160,
    "pct": 0.83
  },
  "354500": {
    "name": "ACE 코스닥150",
    "price": 19695,
    "diff": 150,
    "pct": 0.77
  },
  "261070": {
    "name": "TIGER 코스닥150바이오테크",
    "price": 19050,
    "diff": -240,
    "pct": -1.24
  },
  "316670": {
    "name": "KIWOOM 코스닥150",
    "price": 9750,
    "diff": 65,
    "pct": 0.67
  },
  "450910": {
    "name": "SOL 코스닥150",
    "price": 19140,
    "diff": 110,
    "pct": 0.58
  },
  "461580": {
    "name": "TIGER 코스닥글로벌",
    "price": 19270,
    "diff": 285,
    "pct": 1.5
  },
  "261060": {
    "name": "TIGER 코스닥150IT",
    "price": 26835,
    "diff": 485,
    "pct": 1.84
  },
  "461450": {
    "name": "KODEX 코스닥글로벌",
    "price": 18910,
    "diff": 140,
    "pct": 0.75
  },
  "304770": {
    "name": "HANARO 코스닥150",
    "price": 19515,
    "diff": 145,
    "pct": 0.75
  },
  "301400": {
    "name": "PLUS 코스닥150",
    "price": 19730,
    "diff": 70,
    "pct": 0.36
  },
  "385720": {
    "name": "TIME 코스피액티브",
    "price": 22895,
    "diff": 390,
    "pct": 1.73
  },
  "302450": {
    "name": "RISE 코스피",
    "price": 64875,
    "diff": 1225,
    "pct": 1.92
  },
  "292150": {
    "name": "TIGER 코리아TOP10",
    "price": 33440,
    "diff": 780,
    "pct": 2.39
  },
  "462330": {
    "name": "KODEX 2차전지산업레버리지",
    "price": 1949,
    "diff": 47,
    "pct": 2.47
  },
  "140950": {
    "name": "파워 코스피100",
    "price": 73360,
    "diff": 1215,
    "pct": 1.68
  },
  "226380": {
    "name": "ACE Fn성장소비주도주",
    "price": 6795,
    "diff": 135,
    "pct": 2.03
  },
  "152500": {
    "name": "ACE 레버리지",
    "price": 41935,
    "diff": 1620,
    "pct": 4.02
  },
  "105190": {
    "name": "ACE 200",
    "price": 95070,
    "diff": 1850,
    "pct": 1.98
  },
  "005930": {
    "name": "삼성전자",
    "price": 217500,
    "diff": 6500,
    "pct": 3.08
  },
  "000660": {
    "name": "SK하이닉스",
    "price": 1153000,
    "diff": 17000,
    "pct": 1.5
  },
  "009150": {
    "name": "삼성전기",
    "price": 639000,
    "diff": 25000,
    "pct": 4.07
  },
  "042700": {
    "name": "한미반도체",
    "price": 292000,
    "diff": -3000,
    "pct": -1.02
  },
  "058470": {
    "name": "리노공업",
    "price": 114500,
    "diff": 1700,
    "pct": 1.51
  },
  "240810": {
    "name": "원익IPS",
    "price": 120700,
    "diff": -1900,
    "pct": -1.55
  },
  "039030": {
    "name": "이오테크닉스",
    "price": 471000,
    "diff": -1000,
    "pct": -0.21
  },
  "000990": {
    "name": "DB하이텍",
    "price": 103300,
    "diff": 4700,
    "pct": 4.77
  },
  "403870": {
    "name": "HPSP",
    "price": 44100,
    "diff": 1550,
    "pct": 3.64
  },
  "036930": {
    "name": "주성엔지니어링",
    "price": 72300,
    "diff": 1700,
    "pct": 2.41
  },
  "095340": {
    "name": "ISC",
    "price": 221000,
    "diff": -3500,
    "pct": -1.56
  },
  "084370": {
    "name": "유진테크",
    "price": 134200,
    "diff": 5300,
    "pct": 4.11
  },
  "357780": {
    "name": "솔브레인",
    "price": 431000,
    "diff": 5500,
    "pct": 1.29
  },
  "440110": {
    "name": "파두",
    "price": 57500,
    "diff": -3400,
    "pct": -5.58
  },
  "064760": {
    "name": "티씨케이",
    "price": 301000,
    "diff": 29500,
    "pct": 10.87
  },
  "005290": {
    "name": "동진쎄미켐",
    "price": 56700,
    "diff": 200,
    "pct": 0.35
  },
  "031980": {
    "name": "피에스케이홀딩스",
    "price": 122800,
    "diff": 9500,
    "pct": 8.38
  },
  "089030": {
    "name": "테크윙",
    "price": 57400,
    "diff": -200,
    "pct": -0.35
  },
  "232140": {
    "name": "와이씨",
    "price": 19970,
    "diff": -20,
    "pct": -0.1
  },
  "095610": {
    "name": "테스",
    "price": 90300,
    "diff": 200,
    "pct": 0.22
  },
  "089970": {
    "name": "브이엠",
    "price": 50300,
    "diff": 300,
    "pct": 0.6
  },
  "487240": {
    "name": "KODEX AI전력핵심설비",
    "price": 38595,
    "diff": 310,
    "pct": 0.81
  },
  "010120": {
    "name": "LS ELECTRIC",
    "price": 188600,
    "diff": 1800,
    "pct": 0.96
  },
  "298040": {
    "name": "효성중공업",
    "price": 2981000,
    "diff": 16000,
    "pct": 0.54
  },
  "267260": {
    "name": "HD현대일렉트릭",
    "price": 1084000,
    "diff": 34000,
    "pct": 3.24
  },
  "006260": {
    "name": "LS",
    "price": 334500,
    "diff": -9000,
    "pct": -2.62
  },
  "001440": {
    "name": "대한전선",
    "price": 41950,
    "diff": 700,
    "pct": 1.7
  },
  "103590": {
    "name": "일진전기",
    "price": 86100,
    "diff": -700,
    "pct": -0.81
  },
  "062040": {
    "name": "산일전기",
    "price": 188300,
    "diff": -6000,
    "pct": -3.09
  },
  "033100": {
    "name": "제룡전기",
    "price": 51700,
    "diff": 300,
    "pct": 0.58
  },
  "000500": {
    "name": "가온전선",
    "price": 142500,
    "diff": 14500,
    "pct": 11.33
  },
  "060370": {
    "name": "LS마린솔루션",
    "price": 32300,
    "diff": 650,
    "pct": 2.05
  },
  "229640": {
    "name": "LS에코에너지",
    "price": 56200,
    "diff": 5600,
    "pct": 11.07
  },
  "272210": {
    "name": "한화시스템",
    "price": 131600,
    "diff": 100,
    "pct": 0.08
  },
  "079550": {
    "name": "LIG디펜스앤에어로스페이스",
    "price": 885000,
    "diff": -8000,
    "pct": -0.9
  },
  "099320": {
    "name": "쎄트렉아이",
    "price": 173900,
    "diff": 1600,
    "pct": 0.93
  },
  "189300": {
    "name": "인텔리안테크",
    "price": 134200,
    "diff": -2800,
    "pct": -2.04
  },
  "077970": {
    "name": "STX엔진",
    "price": 33850,
    "diff": -150,
    "pct": -0.44
  },
  "329180": {
    "name": "HD현대중공업",
    "price": 493500,
    "diff": 19000,
    "pct": 4.0
  },
  "042660": {
    "name": "한화오션",
    "price": 131100,
    "diff": 5300,
    "pct": 4.21
  },
  "047810": {
    "name": "한국항공우주",
    "price": 189900,
    "diff": -100,
    "pct": -0.05
  },
  "064350": {
    "name": "현대로템",
    "price": 217000,
    "diff": 7000,
    "pct": 3.33
  },
  "103140": {
    "name": "풍산",
    "price": 102100,
    "diff": 1500,
    "pct": 1.49
  },
  "003570": {
    "name": "SNT다이내믹스",
    "price": 56400,
    "diff": 2000,
    "pct": 3.68
  },
  "484870": {
    "name": "엠앤씨솔루션",
    "price": 118000,
    "diff": 1600,
    "pct": 1.37
  },
  "214430": {
    "name": "아이쓰리시스템",
    "price": 96300,
    "diff": -400,
    "pct": -0.41
  },
  "012450": {
    "name": "한화에어로스페이스",
    "price": 1514000,
    "diff": 5000,
    "pct": 0.33
  },
  "364980": {
    "name": "TIGER 2차전지TOP10",
    "price": 11395,
    "diff": 165,
    "pct": 1.47
  },
  "461950": {
    "name": "KODEX 2차전지핵심소재10",
    "price": 7070,
    "diff": 50,
    "pct": 0.71
  },
  "006400": {
    "name": "삼성SDI",
    "price": 477500,
    "diff": 6500,
    "pct": 1.38
  },
  "005490": {
    "name": "POSCO홀딩스",
    "price": 369500,
    "diff": 1500,
    "pct": 0.41
  },
  "373220": {
    "name": "LG에너지솔루션",
    "price": 415000,
    "diff": 7000,
    "pct": 1.72
  },
  "051910": {
    "name": "LG화학",
    "price": 355500,
    "diff": 1500,
    "pct": 0.42
  },
  "086520": {
    "name": "에코프로",
    "price": 148900,
    "diff": 1000,
    "pct": 0.68
  },
  "247540": {
    "name": "에코프로비엠",
    "price": 205000,
    "diff": 2500,
    "pct": 1.23
  },
  "003670": {
    "name": "포스코퓨처엠",
    "price": 223500,
    "diff": 6000,
    "pct": 2.76
  },
  "096770": {
    "name": "SK이노베이션",
    "price": 126400,
    "diff": 4800,
    "pct": 3.95
  },
  "450080": {
    "name": "에코프로머티",
    "price": 71600,
    "diff": 700,
    "pct": 0.99
  },
  "066970": {
    "name": "엘앤에프",
    "price": 169600,
    "diff": -1000,
    "pct": -0.59
  },
  "011790": {
    "name": "SKC",
    "price": 121500,
    "diff": 21700,
    "pct": 21.74
  },
  "020150": {
    "name": "롯데에너지머티리얼즈",
    "price": 48800,
    "diff": 2600,
    "pct": 5.63
  },
  "361610": {
    "name": "SK아이이테크놀로지",
    "price": 23600,
    "diff": 650,
    "pct": 2.83
  },
  "005070": {
    "name": "코스모신소재",
    "price": 55200,
    "diff": 200,
    "pct": 0.36
  },
  "348370": {
    "name": "엔켐",
    "price": 43050,
    "diff": 3900,
    "pct": 9.96
  },
  "121600": {
    "name": "나노신소재",
    "price": 76500,
    "diff": 700,
    "pct": 0.92
  }
}