{
  "139320": {
    "name": "TIGER 금은선물(H)",
    "price": 16845,
    "diff": -40,
    "pct": -0.24
  },
  "229200": {
    "name": "KODEX 코스닥150",
    "price": 13800,
    "diff": -545,
    "pct": -3.8
  },
  "498400": {
    "name": "KODEX 200타겟위클리커버드콜",
    "price": 21180,
    "diff": -1080,
    "pct": -4.85
  },
  "472150": {
    "name": "TIGER 배당커버드콜액티브",
    "price": 21480,
    "diff": -1265,
    "pct": -5.56
  },
  "441640": {
    "name": "KODEX 미국배당커버드콜액티브",
    "price": 13192,
    "diff": -28,
    "pct": -0.21
  },
  "483320": {
    "name": "ACE 엔비디아밸류체인액티브",
    "price": 26050,
    "diff": -1310,
    "pct": -4.79
  },
  "426030": {
    "name": "TIME 미국나스닥100액티브",
    "price": 50430,
    "diff": -3250,
    "pct": -6.05
  },
  "491620": {
    "name": "RISE 미국테크100데일리고정커버드콜",
    "price": 11605,
    "diff": 30,
    "pct": 0.26
  },
  "478150": {
    "name": "TIME 글로벌우주테크&방산액티브",
    "price": 21370,
    "diff": -40,
    "pct": -0.19
  },
  "0131V0": {
    "name": "1Q 미국우주항공테크",
    "price": 11465,
    "diff": -325,
    "pct": -2.76
  },
  "0040X0": {
    "name": "SOL 팔란티어미국채커버드콜혼합",
    "price": 9575,
    "diff": -40,
    "pct": -0.42
  },
  "0023A0": {
    "name": "SOL 미국양자컴퓨팅TOP10",
    "price": 26175,
    "diff": -1325,
    "pct": -4.82
  },
  "0117V0": {
    "name": "TIGER 코리아AI전력기기TOP3플러스",
    "price": 18315,
    "diff": -780,
    "pct": -4.08
  },
  "456600": {
    "name": "TIME 글로벌AI인공지능액티브",
    "price": 62495,
    "diff": -3510,
    "pct": -5.32
  },
  "490590": {
    "name": "RISE 미국AI밸류체인데일리고정커버드콜",
    "price": 15345,
    "diff": -230,
    "pct": -1.48
  },
  "493810": {
    "name": "TIGER 미국AI빅테크10타겟데일리커버드콜",
    "price": 12385,
    "diff": 165,
    "pct": 1.35
  },
  "483330": {
    "name": "ACE 마이크로소프트밸류체인액티브",
    "price": 14555,
    "diff": 95,
    "pct": 0.66
  },
  "396500": {
    "name": "TIGER 반도체TOP10",
    "price": 38410,
    "diff": -3275,
    "pct": -7.86
  },
  "0093A0": {
    "name": "RISE AI반도체TOP10",
    "price": 34582,
    "diff": -2278,
    "pct": -6.18
  },
  "475300": {
    "name": "SOL 반도체전공정",
    "price": 25790,
    "diff": -1000,
    "pct": -3.73
  },
  "395270": {
    "name": "HANARO Fn K-반도체",
    "price": 59350,
    "diff": -5210,
    "pct": -8.07
  },
  "449450": {
    "name": "PLUS K방산",
    "price": 54825,
    "diff": 1050,
    "pct": 1.95
  },
  "490480": {
    "name": "SOL K방산",
    "price": 29030,
    "diff": 645,
    "pct": 2.27
  },
  "0080G0": {
    "name": "KODEX 방산TOP10",
    "price": 10715,
    "diff": 100,
    "pct": 0.94
  },
  "494670": {
    "name": "TIGER 조선TOP10",
    "price": 22455,
    "diff": 910,
    "pct": 4.22
  },
  "480030": {
    "name": "ACE 미국500데일리타겟커버드콜(합성)",
    "price": 10930,
    "diff": -10,
    "pct": -0.09
  },
  "0115D0": {
    "name": "KODEX 조선TOP10",
    "price": 7950,
    "diff": 305,
    "pct": 3.99
  },
  "305540": {
    "name": "TIGER 2차전지테마",
    "price": 17205,
    "diff": -185,
    "pct": -1.06
  },
  "305720": {
    "name": "KODEX 2차전지산업",
    "price": 13640,
    "diff": -185,
    "pct": -1.34
  },
  "232080": {
    "name": "TIGER 코스닥150",
    "price": 14070,
    "diff": -535,
    "pct": -3.66
  },
  "270810": {
    "name": "RISE 코스닥150",
    "price": 13705,
    "diff": -550,
    "pct": -3.86
  },
  "354500": {
    "name": "ACE 코스닥150",
    "price": 13925,
    "diff": -525,
    "pct": -3.63
  },
  "261070": {
    "name": "TIGER 코스닥150바이오테크",
    "price": 11740,
    "diff": -305,
    "pct": -2.53
  },
  "316670": {
    "name": "KIWOOM 코스닥150",
    "price": 6860,
    "diff": -275,
    "pct": -3.85
  },
  "450910": {
    "name": "SOL 코스닥150",
    "price": 13455,
    "diff": -560,
    "pct": -4.0
  },
  "461580": {
    "name": "TIGER 코스닥글로벌",
    "price": 15355,
    "diff": -590,
    "pct": -3.7
  },
  "261060": {
    "name": "TIGER 코스닥150IT",
    "price": 24435,
    "diff": -1475,
    "pct": -5.69
  },
  "461450": {
    "name": "KODEX 코스닥글로벌",
    "price": 15080,
    "diff": -610,
    "pct": -3.89
  },
  "304770": {
    "name": "HANARO 코스닥150",
    "price": 13775,
    "diff": -565,
    "pct": -3.94
  },
  "301400": {
    "name": "PLUS 코스닥150",
    "price": 13710,
    "diff": -705,
    "pct": -4.89
  },
  "385720": {
    "name": "TIME 코스피액티브",
    "price": 26260,
    "diff": -1355,
    "pct": -4.91
  },
  "302450": {
    "name": "RISE 코스피",
    "price": 71970,
    "diff": -3500,
    "pct": -4.64
  },
  "292150": {
    "name": "TIGER 코리아TOP10",
    "price": 39050,
    "diff": -2055,
    "pct": -5.0
  },
  "462330": {
    "name": "KODEX 2차전지산업레버리지",
    "price": 959,
    "diff": -18,
    "pct": -1.84
  },
  "140950": {
    "name": "파워 코스피100",
    "price": 86910,
    "diff": -5060,
    "pct": -5.5
  },
  "226380": {
    "name": "ACE Fn성장소비주도주",
    "price": 5520,
    "diff": 5,
    "pct": 0.09
  },
  "152500": {
    "name": "ACE 레버리지",
    "price": 51100,
    "diff": -5815,
    "pct": -10.22
  },
  "105190": {
    "name": "ACE 200",
    "price": 111070,
    "diff": -5995,
    "pct": -5.12
  },
  "005930": {
    "name": "삼성전자",
    "price": 261000,
    "diff": -18500,
    "pct": -6.62
  },
  "000660": {
    "name": "SK하이닉스",
    "price": 1886000,
    "diff": -196000,
    "pct": -9.41
  },
  "009150": {
    "name": "삼성전기",
    "price": 1323000,
    "diff": -90000,
    "pct": -6.37
  },
  "042700": {
    "name": "한미반도체",
    "price": 252500,
    "diff": -17000,
    "pct": -6.31
  },
  "058470": {
    "name": "리노공업",
    "price": 74200,
    "diff": -3700,
    "pct": -4.75
  },
  "240810": {
    "name": "원익IPS",
    "price": 145700,
    "diff": 3000,
    "pct": 2.1
  },
  "039030": {
    "name": "이오테크닉스",
    "price": 357000,
    "diff": -28000,
    "pct": -7.27
  },
  "000990": {
    "name": "DB하이텍",
    "price": 113100,
    "diff": -7700,
    "pct": -6.37
  },
  "403870": {
    "name": "HPSP",
    "price": 43450,
    "diff": -3250,
    "pct": -6.96
  },
  "036930": {
    "name": "주성엔지니어링",
    "price": 198300,
    "diff": -11200,
    "pct": -5.35
  },
  "095340": {
    "name": "ISC",
    "price": 148500,
    "diff": -10000,
    "pct": -6.31
  },
  "084370": {
    "name": "유진테크",
    "price": 152300,
    "diff": -10500,
    "pct": -6.45
  },
  "357780": {
    "name": "솔브레인",
    "price": 296000,
    "diff": -10500,
    "pct": -3.43
  },
  "440110": {
    "name": "파두",
    "price": 72300,
    "diff": -7600,
    "pct": -9.51
  },
  "064760": {
    "name": "티씨케이",
    "price": 216500,
    "diff": -10500,
    "pct": -4.63
  },
  "005290": {
    "name": "동진쎄미켐",
    "price": 44200,
    "diff": -2250,
    "pct": -4.84
  },
  "031980": {
    "name": "피에스케이홀딩스",
    "price": 144000,
    "diff": -12200,
    "pct": -7.81
  },
  "089030": {
    "name": "테크윙",
    "price": 51100,
    "diff": -800,
    "pct": -1.54
  },
  "232140": {
    "name": "와이씨",
    "price": 10160,
    "diff": -690,
    "pct": -6.36
  },
  "095610": {
    "name": "테스",
    "price": 201500,
    "diff": -12500,
    "pct": -5.84
  },
  "089970": {
    "name": "브이엠",
    "price": 111000,
    "diff": -4900,
    "pct": -4.23
  },
  "487240": {
    "name": "KODEX AI전력핵심설비",
    "price": 34650,
    "diff": -1490,
    "pct": -4.12
  },
  "010120": {
    "name": "LS ELECTRIC",
    "price": 190300,
    "diff": -11200,
    "pct": -5.56
  },
  "298040": {
    "name": "효성중공업",
    "price": 2819000,
    "diff": -49000,
    "pct": -1.71
  },
  "267260": {
    "name": "HD현대일렉트릭",
    "price": 799000,
    "diff": -24000,
    "pct": -2.92
  },
  "006260": {
    "name": "LS",
    "price": 293500,
    "diff": -11500,
    "pct": -3.77
  },
  "001440": {
    "name": "대한전선",
    "price": 28150,
    "diff": -1800,
    "pct": -6.01
  },
  "103590": {
    "name": "일진전기",
    "price": 60400,
    "diff": -3300,
    "pct": -5.18
  },
  "062040": {
    "name": "산일전기",
    "price": 172700,
    "diff": -6500,
    "pct": -3.63
  },
  "033100": {
    "name": "제룡전기",
    "price": 43450,
    "diff": -3250,
    "pct": -6.96
  },
  "000500": {
    "name": "가온전선",
    "price": 202000,
    "diff": -18500,
    "pct": -8.39
  },
  "060370": {
    "name": "LS마린솔루션",
    "price": 27350,
    "diff": -250,
    "pct": -0.91
  },
  "229640": {
    "name": "LS에코에너지",
    "price": 43650,
    "diff": -1550,
    "pct": -3.43
  },
  "272210": {
    "name": "한화시스템",
    "price": 67000,
    "diff": 1200,
    "pct": 1.82
  },
  "079550": {
    "name": "LIG디펜스앤에어로스페이스",
    "price": 758000,
    "diff": 1000,
    "pct": 0.13
  },
  "099320": {
    "name": "쎄트렉아이",
    "price": 79300,
    "diff": -1400,
    "pct": -1.73
  },
  "189300": {
    "name": "인텔리안테크",
    "price": 63900,
    "diff": -3200,
    "pct": -4.77
  },
  "077970": {
    "name": "STX엔진",
    "price": 25450,
    "diff": -150,
    "pct": -0.59
  },
  "329180": {
    "name": "HD현대중공업",
    "price": 486500,
    "diff": 15500,
    "pct": 3.29
  },
  "042660": {
    "name": "한화오션",
    "price": 86500,
    "diff": 4500,
    "pct": 5.49
  },
  "047810": {
    "name": "한국항공우주",
    "price": 152300,
    "diff": 4800,
    "pct": 3.25
  },
  "064350": {
    "name": "현대로템",
    "price": 163000,
    "diff": -4700,
    "pct": -2.8
  },
  "103140": {
    "name": "풍산",
    "price": 63100,
    "diff": 700,
    "pct": 1.12
  },
  "003570": {
    "name": "SNT다이내믹스",
    "price": 34325,
    "diff": -375,
    "pct": -1.08
  },
  "484870": {
    "name": "엠앤씨솔루션",
    "price": 22750,
    "diff": -800,
    "pct": -3.4
  },
  "214430": {
    "name": "아이쓰리시스템",
    "price": 58000,
    "diff": -2400,
    "pct": -3.97
  },
  "012450": {
    "name": "한화에어로스페이스",
    "price": 967000,
    "diff": 38000,
    "pct": 4.09
  },
  "364980": {
    "name": "TIGER 2차전지TOP10",
    "price": 9340,
    "diff": -90,
    "pct": -0.95
  },
  "461950": {
    "name": "KODEX 2차전지핵심소재10",
    "price": 4590,
    "diff": -105,
    "pct": -2.24
  },
  "006400": {
    "name": "삼성SDI",
    "price": 440000,
    "diff": -14000,
    "pct": -3.08
  },
  "005490": {
    "name": "POSCO홀딩스",
    "price": 315750,
    "diff": 1250,
    "pct": 0.4
  },
  "373220": {
    "name": "LG에너지솔루션",
    "price": 341500,
    "diff": 6500,
    "pct": 1.94
  },
  "051910": {
    "name": "LG화학",
    "price": 266000,
    "diff": 1500,
    "pct": 0.57
  },
  "086520": {
    "name": "에코프로",
    "price": 81200,
    "diff": -5200,
    "pct": -6.02
  },
  "247540": {
    "name": "에코프로비엠",
    "price": 114200,
    "diff": -6700,
    "pct": -5.54
  },
  "003670": {
    "name": "포스코퓨처엠",
    "price": 149100,
    "diff": -4100,
    "pct": -2.68
  },
  "096770": {
    "name": "SK이노베이션",
    "price": 124100,
    "diff": 7100,
    "pct": 6.07
  },
  "450080": {
    "name": "에코프로머티",
    "price": 36700,
    "diff": -900,
    "pct": -2.39
  },
  "066970": {
    "name": "엘앤에프",
    "price": 93800,
    "diff": -1300,
    "pct": -1.37
  },
  "011790": {
    "name": "SKC",
    "price": 86900,
    "diff": -3500,
    "pct": -3.87
  },
  "020150": {
    "name": "롯데에너지머티리얼즈",
    "price": 32950,
    "diff": -1250,
    "pct": -3.65
  },
  "361610": {
    "name": "SK아이이테크놀로지",
    "price": 14520,
    "diff": -20,
    "pct": -0.14
  },
  "005070": {
    "name": "코스모신소재",
    "price": 38800,
    "diff": -700,
    "pct": -1.77
  },
  "348370": {
    "name": "엔켐",
    "price": 24800,
    "diff": 3400,
    "pct": 15.89
  },
  "121600": {
    "name": "나노신소재",
    "price": 44500,
    "diff": -1650,
    "pct": -3.58
  }
}